setup.py
py_distributions_dsnd/Binomialdistribution.py
py_distributions_dsnd/Gaussiandistribution.py
py_distributions_dsnd/Generaldistribution.py
py_distributions_dsnd/__init__.py
py_distributions_dsnd.egg-info/PKG-INFO
py_distributions_dsnd.egg-info/SOURCES.txt
py_distributions_dsnd.egg-info/dependency_links.txt
py_distributions_dsnd.egg-info/not-zip-safe
py_distributions_dsnd.egg-info/top_level.txt